dr_zoidberg-0.1.3.15.dist-info/DESCRIPTION.rst
dr_zoidberg-0.1.3.15.dist-info/METADATA
dr_zoidberg-0.1.3.15.dist-info/RECORD
dr_zoidberg-0.1.3.15.dist-info/WHEEL
dr_zoidberg-0.1.3.15.dist-info/entry_points.txt
dr_zoidberg-0.1.3.15.dist-info/metadata.json
dr_zoidberg-0.1.3.15.dist-info/top_level.txt
zoidberg/__init__.py
zoidberg/cli.py
zoidberg/scrapy.cfg
zoidberg/zoidberg.py
zoidberg/zoidberg_main.py
zoidberg/scraper/__init__.py
zoidberg/scraper/items.py
zoidberg/scraper/middlewares.py
zoidberg/scraper/pipelines.py
zoidberg/scraper/settings.py
zoidberg/scraper/zoidberg.py
zoidberg/scraper/__pycache__/__init__.cpython-36.pyc
zoidberg/scraper/__pycache__/items.cpython-36.pyc
zoidberg/scraper/__pycache__/pipelines.cpython-36.pyc
zoidberg/scraper/__pycache__/settings.cpython-36.pyc
zoidberg/scraper/__pycache__/zoidberg.cpython-36.pyc
zoidberg/scraper/db/es/es_db.json
zoidberg/scraper/spiders/__init__.py
zoidberg/scraper/spiders/es_spider.py
zoidberg/scraper/spiders/zoidberg_spider.py
zoidberg/scraper/spiders/__pycache__/__init__.cpython-36.pyc
zoidberg/scraper/spiders/__pycache__/es_spider.cpython-36.pyc
zoidberg/scraper/spiders/__pycache__/zoidberg_spider.cpython-36.pyc
zoidberg/scraper/spiders/es/__init__.py
zoidberg/scraper/spiders/es/es_spider.py
