Metadata-Version: 2.0
Name: dr-zoidberg
Version: 0.1.3.15
Summary: Are you ready to operate, Doctor? - I'd love to, but first I have to perform surgery.
Home-page: https://github.com/ginopalazzo/zoidberg
Author: Gino Palazzo
Author-email: ginopalazzo@gmail.com
License: MIT license
Keywords: zoidberg drzoidberg dr-zoidberg doctor
Platform: UNKNOWN
Classifier: Development Status :: 2 - Pre-Alpha
Classifier: Intended Audience :: Developers
Classifier: License :: OSI Approved :: MIT License
Classifier: Natural Language :: English
Classifier: Programming Language :: Python :: 2
Classifier: Programming Language :: Python :: 2.7
Classifier: Programming Language :: Python :: 3
Classifier: Programming Language :: Python :: 3.4
Classifier: Programming Language :: Python :: 3.5
Classifier: Programming Language :: Python :: 3.6
Requires-Dist: Click (>=6.0)
Requires-Dist: Scrapy (>=1.5.0)
